[
  {
    "periodId": 1,
    "duration": {
      "startTime": "2022-08-31T00:00:00.000+00:00",
      "endTime": "2022-09-07T00:00:00.000+00:00"
    },
    "claimWindow": {
      "startTime": "2022-09-07T00:00:00.000+00:00",
      "endTime": "2022-09-21T00:00:00.000+00:00"
    },
    "stakingReward": "256409999999999999999944",
    "feeReward": "22785256210328293121"
  },
  {
    "periodId": 2,
    "duration": {
      "startTime": "2022-09-07T00:00:00.000+00:00",
      "endTime": "2022-09-14T00:00:00.000+00:00"
    },
    "claimWindow": {
      "startTime": "2022-09-14T00:00:00.000+00:00",
      "endTime": "2022-09-28T00:00:00.000+00:00"
    },
    "stakingReward": "256409999999999999999935",
    "feeReward": "46002866098306796408"
  },
  {
    "periodId": 3,
    "duration": {
      "startTime": "2022-09-14T00:00:00.000+00:00",
      "endTime": "2022-09-21T00:00:00.000+00:00"
    },
    "claimWindow": {
      "startTime": "2022-09-21T00:00:00.000+00:00",
      "endTime": "2022-10-05T00:00:00.000+00:00"
    },
    "stakingReward": "257978523738048897905584",
    "feeReward": "64233034123713699052"
  },
  {
    "periodId": 4,
    "duration": {
      "startTime": "2022-09-21T00:00:00.000+00:00",
      "endTime": "2022-09-28T00:00:00.000+00:00"
    },
    "claimWindow": {
      "startTime": "2022-09-28T00:00:00.000+00:00",
      "endTime": "2022-10-12T00:00:00.000+00:00"
    },
    "stakingReward": "259627539632231304854557",
    "feeReward": "40104001107698140224"
  },
  {
    "periodId": 5,
    "duration": {
      "startTime": "2022-09-28T00:00:00.000+00:00",
      "endTime": "2022-10-05T00:00:00.000+00:00"
    },
    "claimWindow": {
      "startTime": "2022-10-05T00:00:00.000+00:00",
      "endTime": "2022-10-19T00:00:00.000+00:00"
    },
    "stakingReward": "259432541934339034137385",
    "feeReward": "13218067072074831956"
  },
  {
    "periodId": 6,
    "duration": {
      "startTime": "2022-10-05T00:00:00.000+00:00",
      "endTime": "2022-10-12T00:00:00.000+00:00"
    },
    "claimWindow": {
      "startTime": "2022-10-12T00:00:00.000+00:00",
      "endTime": "2022-10-26T00:00:00.000+00:00"
    },
    "stakingReward": "258884785927479328493700",
    "feeReward": "127377804158077864711"
  },
  {
    "periodId": 7,
    "duration": {
      "startTime": "2022-10-12T00:00:00.000+00:00",
      "endTime": "2022-10-19T00:00:00.000+00:00"
    },
    "claimWindow": {
      "startTime": "2022-10-19T00:00:00.000+00:00",
      "endTime": "2022-11-02T00:00:00.000+00:00"
    },
    "stakingReward": "258193211749586483432812",
    "feeReward": "225688560409123585513"
  },
  {
    "periodId": 8,
    "duration": {
      "startTime": "2022-10-19T00:00:00.000+00:00",
      "endTime": "2022-10-26T00:00:00.000+00:00"
    },
    "claimWindow": {
      "startTime": "2022-10-26T00:00:00.000+00:00",
      "endTime": "2022-11-09T00:00:00.000+00:00"
    },
    "stakingReward": "258048142812415810463262",
    "feeReward": "110807930749312436289"
  }
]
